README.rst
setup.py
pystuck/__init__.py
pystuck/greenlets.py
pystuck/ipython.py
pystuck/rpyc_tools.py
pystuck/thread_probe.py
pystuck.egg-info/PKG-INFO
pystuck.egg-info/SOURCES.txt
pystuck.egg-info/dependency_links.txt
pystuck.egg-info/entry_points.txt
pystuck.egg-info/requires.txt
pystuck.egg-info/top_level.txt