Metadata-Version: 1.1
Name: pystuck
Version: 0.8.4
Summary: 
